skainet/__init__.py
skainet/__main__.py
skainet/audio.py
skainet/config.ini
skainet/config.py
skainet/data.py
skainet/file.py
skainet/image.py
skainet/model.py
skainet/moderate.py
skainet/text.py
skainet/utils.py
skainet-0.1.0.dist-info/METADATA
skainet-0.1.0.dist-info/WHEEL
skainet-0.1.0.dist-info/entry_points.txt
skainet-0.1.0.dist-info/top_level.txt
skainet-0.1.0.dist-info/RECORD
